[{"Scrip_Name": "Ambo Agritec Ltd", "INDUSTRY": "Edible Oil", "scrip_id": "AMBOAGRI", "Mktcap": "23.49", "ANN_TITLE": "Clarification On Late Submission With Respect To Outcome Of Board Meeting", "NEWS_DT": "2023-06-29T09:15:30.893", "ConcallLink": [{"ANN_TITLE": "Notes Taken For The Fines Imposed", "LINK": "https://www.bseindia.com/xml-data/corpfiling/AttachLive/8fe37472-57e2-4240-8cf7-62cc1e6b9f29.pdf"}, {"ANN_TITLE": "Clarification On Late Submission With Respect To Outcome Of Board Meeting", "LINK": "https://www.bseindia.com/xml-data/corpfiling/AttachLive/bb31ec02-183a-4a91-a30f-ab04a7f34cbb.pdf"}], "scrip_cd": 543678}, {"Scrip_Name": "Gensol Engineering Ltd", "INDUSTRY": "Consulting Services", "scrip_id": "GENSOL", "Mktcap": "1172.04", "ANN_TITLE": "Receipt Final Approval For Main Board Migration From BSE Limited And National Stock Exchange Of India Limited.", "NEWS_DT": "2023-06-29T00:54:55.433", "ConcallLink": [{"ANN_TITLE": "Receipt Final Approval For Main Board Migration From BSE Limited And National Stock Exchange Of India Limited.", "LINK": "https://www.bseindia.com/xml-data/corpfiling/AttachLive/deef9a5c-356b-4828-b131-35f468c1ddbf.pdf"}], "scrip_cd": 542851}]